magestore_aup/__init__.py
magestore_aup/auto.py
magestore_aup/data/raw_deploy.sh
magestore_aup-2.2.2.dist-info/METADATA
magestore_aup-2.2.2.dist-info/WHEEL
magestore_aup-2.2.2.dist-info/top_level.txt
magestore_aup-2.2.2.dist-info/RECORD
