Metadata-Version: 2.1
Name: magestore-aup
Version: 2.2.2
Summary: Fix get nearly newest version
Home-page: https://magestore.com
Author: Mars
Author-email: mars@trueplus.vn
License: UNKNOWN
Platform: UNKNOWN
Classifier: Programming Language :: Python :: 3
Requires-Python: >=3
Requires-Dist: cryptography (>=2.5)
Requires-Dist: fabric
Requires-Dist: packaging
Requires-Dist: requests
